emanate/__init__.py
emanate/__main__.py
emanate/cli.py
emanate/config.py
emanate/version.py
emanate-8.0.4.dist-info/licenses/LICENSE.txt
emanate-8.0.4.dist-info/METADATA
emanate-8.0.4.dist-info/WHEEL
emanate-8.0.4.dist-info/entry_points.txt
emanate-8.0.4.dist-info/top_level.txt
emanate-8.0.4.dist-info/RECORD
