Metadata-Version: 2.4
Name: emanate
Version: 8.0.4
Summary: Symlink files from one directory to another, similary to Effuse and Stow.
Author-email: Ellen Marie Dash <me@duckie.co>
License-Expression: MIT
Project-URL: repository, https://github.com/duckinator/emanate
Project-URL: documentation, https://emanate-docs.netlify.app/cli.html
Classifier: Programming Language :: Python :: 3
Classifier: Programming Language :: Python :: 3.9
Classifier: Programming Language :: Python :: 3.10
Classifier: Programming Language :: Python :: 3.11
Classifier: Operating System :: OS Independent
Requires-Python: >=3.9
License-File: LICENSE.txt
Provides-Extra: lint
Requires-Dist: bork; extra == "lint"
Requires-Dist: ruff; extra == "lint"
Provides-Extra: test
Requires-Dist: bork; extra == "test"
Requires-Dist: pytest~=7.4; extra == "test"
Requires-Dist: mypy~=1.6.1; extra == "test"
Requires-Dist: pytest-mypy~=0.10.3; extra == "test"
Provides-Extra: docs
Requires-Dist: sphinx; extra == "docs"
Requires-Dist: sphinx-rtd-theme; extra == "docs"
Requires-Dist: sphinx-argparse; extra == "docs"
Dynamic: license-file
